AUTHOR
LICENSE
MANIFEST.in
README.txt
setup.py
caps/__init__.py
caps/info.py
caps/toy_datasets.py
caps.egg-info/PKG-INFO
caps.egg-info/SOURCES.txt
caps.egg-info/dependency_links.txt
caps.egg-info/requires.txt
caps.egg-info/top_level.txt
caps/dicom_converter/__init__.py
caps/dicom_converter/dicom_deidentifier.py
caps/dicom_converter/dicom_deidentifier_v2.py
caps/dicom_converter/nifti_converter.py
caps/dicom_converter/base/__init__.py
caps/dicom_converter/base/csa2.py
caps/dicom_converter/base/split_series.py
caps/dicom_converter/base/tools.py
caps/diffusion_estimation/__init__.py
caps/diffusion_estimation/diffusion_multiprocessing.py
caps/diffusion_estimation/fsl_tensor_estimation.py
caps/diffusion_estimation/fvtk.py
caps/diffusion_estimation/integrals.py
caps/diffusion_estimation/monomials.py
caps/diffusion_estimation/polynomials.py
caps/diffusion_estimation/py_tensor_estimation.py
caps/diffusion_estimation/tensor_estimation.py
caps/diffusion_estimation/tensor_scalars.py
caps/diffusion_estimation/tensor_utils.py
caps/diffusion_estimation/resources/__init__.py
caps/diffusion_preproc/__init__.py
caps/diffusion_preproc/bet.py
caps/diffusion_preproc/eddy_correction.py
caps/diffusion_preproc/fsl_preproc.py
caps/diffusion_preproc/motion_correction.py
caps/diffusion_preproc/susceptibility_correction.py
caps/diffusion_registration/__init__.py
caps/diffusion_registration/fsl_registration.py
caps/diffusion_registration/reorientation.py
caps/functional_connectivity/__init__.py
caps/functional_connectivity/analysis.py
caps/functional_connectivity/conn.py
caps/functional_connectivity/manager.py
caps/functional_connectivity/matlab_utils.py
caps/functional_connectivity/results.py
caps/functional_connectivity/setup.py
caps/functional_connectivity/spatial_preproc.py
caps/functional_connectivity/temporal_preproc.py
caps/functional_connectivity/matlab_batch/__init__.py
caps/functional_preproc/__init__.py
caps/functional_preproc/pypreprocess_fmri_preproc.py
caps/preclinic_functional/__init__.py
caps/preclinic_functional/bet.py
caps/preclinic_functional/slice_timing.py
caps/preclinic_functional/spm_coregistration.py
