Metadata-Version: 1.1
Name: caps
Version: 0.0.1
Summary: CApsul PipelineS (CAPS)
Home-page: http:/nsap.intra.cea.fr/caps-doc
Author: CAPS developers
Author-email: antoine.grigis@cea.fr
License: CeCILL-B
Platform: OS Independent
Classifier: Development Status :: 3 - Alpha
Classifier: Environment :: Console
Classifier: Operating System :: OS Independent
Classifier: Programming Language :: Python
Classifier: Topic :: Scientific/Engineering
Classifier: Topic :: Utilities
